infomeasure/__init__.py
infomeasure/_version.py
infomeasure/composite_measures/__init__.py
infomeasure/composite_measures/jsd.py
infomeasure/composite_measures/kld.py
infomeasure/estimators/__init__.py
infomeasure/estimators/base.py
infomeasure/estimators/functional.py
infomeasure/estimators/mixins.py
infomeasure/estimators/entropy/__init__.py
infomeasure/estimators/entropy/ansb.py
infomeasure/estimators/entropy/bayes.py
infomeasure/estimators/entropy/bonachela.py
infomeasure/estimators/entropy/chao_shen.py
infomeasure/estimators/entropy/chao_wang_jost.py
infomeasure/estimators/entropy/discrete.py
infomeasure/estimators/entropy/grassberger.py
infomeasure/estimators/entropy/kernel.py
infomeasure/estimators/entropy/kozachenko_leonenko.py
infomeasure/estimators/entropy/miller_madow.py
infomeasure/estimators/entropy/nsb.py
infomeasure/estimators/entropy/ordinal.py
infomeasure/estimators/entropy/renyi.py
infomeasure/estimators/entropy/shrink.py
infomeasure/estimators/entropy/tsallis.py
infomeasure/estimators/entropy/zhang.py
infomeasure/estimators/mutual_information/__init__.py
infomeasure/estimators/mutual_information/ansb.py
infomeasure/estimators/mutual_information/bayes.py
infomeasure/estimators/mutual_information/bonachela.py
infomeasure/estimators/mutual_information/chao_shen.py
infomeasure/estimators/mutual_information/chao_wang_jost.py
infomeasure/estimators/mutual_information/discrete.py
infomeasure/estimators/mutual_information/grassberger.py
infomeasure/estimators/mutual_information/kernel.py
infomeasure/estimators/mutual_information/kraskov_stoegbauer_grassberger.py
infomeasure/estimators/mutual_information/miller_madow.py
infomeasure/estimators/mutual_information/nsb.py
infomeasure/estimators/mutual_information/ordinal.py
infomeasure/estimators/mutual_information/renyi.py
infomeasure/estimators/mutual_information/shrink.py
infomeasure/estimators/mutual_information/tsallis.py
infomeasure/estimators/mutual_information/zhang.py
infomeasure-0.5.1.dist-info/licenses/LICENSE
infomeasure-0.5.1.dist-info/METADATA
infomeasure-0.5.1.dist-info/WHEEL
infomeasure-0.5.1.dist-info/top_level.txt
infomeasure-0.5.1.dist-info/RECORD
