Metadata-Version: 2.4
Name: infomeasure
Version: 0.5.1
Summary: Comprehensive collection of information measures.
Author: Kishor Achary, Massimilliano Zanin
Author-email: Carlson Büth <code@cbueth.de>
Maintainer-email: Carlson Büth <code@cbueth.de>
License-Expression: AGPL-3.0-or-later
Project-URL: Documentation, https://infomeasure.readthedocs.io/
Project-URL: Repository, https://github.com/cbueth/infomeasure
Project-URL: Issues, https://github.com/cbueth/infomeasure/issues
Project-URL: Changelog, https://infomeasure.readthedocs.io/en/latest/changelog/
Keywords: Entropy,Mutual Information,Information Theory,Information Measures
Classifier: Development Status :: 5 - Production/Stable
Classifier: Intended Audience :: Science/Research
Classifier: Intended Audience :: Developers
Classifier: Operating System :: OS Independent
Classifier: Programming Language :: Python :: 3
Classifier: Programming Language :: Python :: 3 :: Only
Classifier: Programming Language :: Python :: 3.11
Classifier: Programming Language :: Python :: 3.12
Classifier: Programming Language :: Python :: 3.13
Classifier: Programming Language :: Python :: 3.14
Classifier: Natural Language :: English
Classifier: Topic :: Scientific/Engineering :: Information Analysis
Classifier: Topic :: Scientific/Engineering :: Physics
Classifier: Topic :: Scientific/Engineering :: Mathematics
Requires-Python: >=3.10
License-File: LICENSE
Requires-Dist: numpy
Requires-Dist: scipy
Requires-Dist: sparse>0.10.0
Requires-Dist: numba
Provides-Extra: lint
Requires-Dist: ruff; extra == "lint"
Provides-Extra: test
Requires-Dist: pytest; extra == "test"
Requires-Dist: pytest-cov; extra == "test"
Requires-Dist: coverage; extra == "test"
Provides-Extra: doc
Requires-Dist: sphinx; extra == "doc"
Requires-Dist: numpydoc; extra == "doc"
Requires-Dist: myst-nb; extra == "doc"
Requires-Dist: sphinx-design; extra == "doc"
Requires-Dist: sphinx-book-theme; extra == "doc"
Requires-Dist: sphinxcontrib-bibtex; extra == "doc"
Requires-Dist: sphinx-automodapi; extra == "doc"
Requires-Dist: matplotlib; extra == "doc"
Provides-Extra: all
Requires-Dist: infomeasure[doc,lint,test]; extra == "all"
Dynamic: license-file
